Workbook

Sheet Dashboard
B2: Stock Market Portfolio Tracker | F2: HOLDING MARKET VALUE | G2: TODAY'S GAIN / LOSS | H2: TODAY'S CHANGE (%) | I2: UNREALISED GAIN/(LOSS) | J2: TOTAL RETURN (%)
B3: SELECT STOCK TO ANALYZE: | C3: TCS | F3: {=IF(C3="ALL PORTFOLIO (MASTER VIEW)", SUM(F6:F16), _xlfn.XLOOKUP(C3, B6:B16, F6:F16))} -> 0 | G3: {=IF(C3="ALL PORTFOLIO (MASTER VIEW)", SUM(G6:G16), _xlfn.XLOOKUP(C3, B6:B16, G6:G16))} -> 0 | H3: {=IF(C3="ALL PORTFOLIO (MASTER VIEW)", G3/(F3-G3), _xlfn.XLOOKUP(C3, B6:B16, H6:H16))} -> 0 | I3: {=IF(C3="ALL PORTFOLIO (MASTER VIEW)", SUM(I6:I16), _xlfn.XLOOKUP(C3, B6:B16, I6:I16))} -> 0 | J3: =I3/(F3-I3) -> 0
B5: Asset / Stock Name | C5: Sector / Industry | D5: Units (Shares) | E5: Current Price (CMP) | F5: Market Value | G5: Today's Change | H5: Today's % | I5: Total Gain / Loss | J5: 12M Trend Graph
B6: HCL TECH | C6: Information Technology | D6: 150 | E6: 1745.5 | F6: =D6*E6 -> 0 | G6: 3240 | H6: 0.0125 | I6: =F6-(D6*Holdings_Data!G2) -> 0
B7: TCS | C7: Information Technology | D7: 40 | E7: 4120 | F7: =D7*E7 -> 0 | G7: 1680 | H7: 0.0103 | I7: =F7-(D7*Holdings_Data!G3) -> 0
B8: INFOSYS | C8: Information Technology | D8: 120 | E8: 1865 | F8: =D8*E8 -> 0 | G8: 2280 | H8: 0.0103 | I8: =F8-(D8*Holdings_Data!G4) -> 0
B9: WIPRO | C9: Information Technology | D9: 250 | E9: 545 | F9: =D9*E9 -> 0 | G9: -875 | H9: -0.0064 | I9: =F9-(D9*Holdings_Data!G5) -> 0
B10: TECH MAHINDRA | C10: Information Technology | D10: 80 | E10: 1640 | F10: =D10*E10 -> 0 | G10: 1280 | H10: 0.0098 | I10: =F10-(D10*Holdings_Data!G6) -> 0
B11: HDFC BANK | C11: Banking & Financials | D11: 100 | E11: 1680 | F11: =D11*E11 -> 0 | G11: 1400 | H11: 0.0084 | I11: =F11-(D11*Holdings_Data!G7) -> 0
B12: AXIS BANK | C12: Banking & Financials | D12: 90 | E12: 1265 | F12: =D12*E12 -> 0 | G12: 810 | H12: 0.0071 | I12: =F12-(D12*Holdings_Data!G8) -> 0
B13: COAL INDIA | C13: Energy & Mining | D13: 300 | E13: 495 | F13: =D13*E13 -> 0 | G13: 1650 | H13: 0.0112 | I13: =F13-(D13*Holdings_Data!G9) -> 0
B14: RVNL (RAIL VIKAS) | C14: Railways & Infrastructure | D14: 350 | E14: 565 | F14: =D14*E14 -> 0 | G14: 4725 | H14: 0.0245 | I14: =F14-(D14*Holdings_Data!G10) -> 0
B15: IRFC (INDIAN RAILWAY) | C15: Railways & Infrastructure | D15: 800 | E15: 185 | F15: =D15*E15 -> 0 | G15: 2400 | H15: 0.0164 | I15: =F15-(D15*Holdings_Data!G11) -> 0
B16: ADITYA BIRLA (ABCAPITAL) | C16: Conglomerate & Financials | D16: 400 | E16: 405 | F16: =D16*E16 -> 0 | G16: 1200 | H16: 0.0075 | I16: =F16-(D16*Holdings_Data!G12) -> 0
B17: Total Portfolio Value | C17: 11 Positions Active | F17: =SUM(F6:F16) -> 0 | G17: =SUM(G6:G16) -> 0 | H17: =G17/(F17-G17) -> 0 | I17: =SUM(I6:I16) -> 0
B18: DYNAMIC ASSET DEEP-DIVE (CONTROLLED BY DROPDOWN C3) | F18: VISUAL ANALYTICS: DONUT, PIE, BAR & 12M TREND CHARTS
B19: {=IF(C3="ALL PORTFOLIO (MASTER VIEW)", "SELECTED: ALL PORTFOLIO OVERVIEW", "SELECTED STOCK: " & C3 & " - " & _xlfn.XLOOKUP(C3, Holdings_Data!B2:B12, Holdings_Data!C2:C12))} -> 0
B20: Company Full Name | D20: {=IF(C3="ALL PORTFOLIO (MASTER VIEW)", "Consolidated 11 Indian Bluechip Assets", _xlfn.XLOOKUP(C3, Holdings_Data!B2:B12, Holdings_Data!C2:C12))} -> 0
B21: NSE / BSE Ticker Symbol | D21: {=IF(C3="ALL PORTFOLIO (MASTER VIEW)", "PORTFOLIO.NSE", _xlfn.XLOOKUP(C3, Holdings_Data!B2:B12, Holdings_Data!A2:A12))} -> 0
B22: Sector / Industry | D22: {=IF(C3="ALL PORTFOLIO (MASTER VIEW)", "Multi-Sector Diversified", _xlfn.XLOOKUP(C3, Holdings_Data!B2:B12, Holdings_Data!D2:D12))} -> 0
B23: Shares / Quantity Held | D23: {=IF(C3="ALL PORTFOLIO (MASTER VIEW)", SUM(Holdings_Data!E2:E12), _xlfn.XLOOKUP(C3, Holdings_Data!B2:B12, Holdings_Data!E2:E12))} -> 0
B24: Average Purchase Price | D24: {=IF(C3="ALL PORTFOLIO (MASTER VIEW)", "-", _xlfn.XLOOKUP(C3, Holdings_Data!B2:B12, Holdings_Data!G2:G12))} -> 0
B25: Current Market Price (CMP) | D25: {=IF(C3="ALL PORTFOLIO (MASTER VIEW)", "-", _xlfn.XLOOKUP(C3, Holdings_Data!B2:B12, Holdings_Data!H2:H12))} -> 0
B26: Total Invested Capital (Cost) | D26: {=IF(C3="ALL PORTFOLIO (MASTER VIEW)", SUM(Holdings_Data!I2:I12), _xlfn.XLOOKUP(C3, Holdings_Data!B2:B12, Holdings_Data!I2:I12))} -> 0
B27: Current Holding Market Value | D27: {=IF(C3="ALL PORTFOLIO (MASTER VIEW)", SUM(Holdings_Data!J2:J12), _xlfn.XLOOKUP(C3, Holdings_Data!B2:B12, Holdings_Data!J2:J12))} -> 0
B28: Total Net Profit / Gain | D28: {=IF(C3="ALL PORTFOLIO (MASTER VIEW)", SUM(Holdings_Data!K2:K12), _xlfn.XLOOKUP(C3, Holdings_Data!B2:B12, Holdings_Data!K2:K12))} -> 0
B29: Return on Investment (ROI %) | D29: {=IF(C3="ALL PORTFOLIO (MASTER VIEW)", SUM(Holdings_Data!K2:K12)/SUM(Holdings_Data!I2:I12), _xlfn.XLOOKUP(C3, Holdings_Data!B2:B12, Holdings_Data!L2:L12))} -> 0
B30: 52-Week Range (High / Low) | D30: {=IF(C3="ALL PORTFOLIO (MASTER VIEW)", "21500 - 26200", _xlfn.XLOOKUP(C3, Holdings_Data!B2:B12, Holdings_Data!Q2:Q12))} -> 0
B31: Annual Dividend Income | D31: {=IF(C3="ALL PORTFOLIO (MASTER VIEW)", SUM(Holdings_Data!P2:P12), _xlfn.XLOOKUP(C3, Holdings_Data!B2:B12, Holdings_Data!P2:P12))} -> 0
B32: Analyst Recommendation | D32: {=IF(C3="ALL PORTFOLIO (MASTER VIEW)", "BULLISH / OVERWEIGHT", _xlfn.XLOOKUP(C3, Holdings_Data!B2:B12, Holdings_Data!R2:R12))} -> 0
B33: Portfolio Weight (%) | D33: {=IF(C3="ALL PORTFOLIO (MASTER VIEW)", 1, _xlfn.XLOOKUP(C3, Holdings_Data!B2:B12, Holdings_Data!J2:J12)/SUM(Holdings_Data!J2:J12))} -> 0
B40: ASSET ALLOCATION BREAKDOWN (PIE CHART OF ALL 11 HOLDINGS) | F40: TOP BLUECHIPS 12-MONTH RETURN TRAJECTORY COMPARISON (MULTI-LINE)

Sheet Holdings_Data
A1: Symbol / Ticker | B1: Stock Key | C1: Company Name | D1: Industry / Sector | E1: Quantity (Shares) | F1: Purchase Date | G1: Avg Buy Price | H1: Current Price | I1: Total Cost Basis | J1: Market Value | K1: Unrealized Gain/(Loss) | L1: ROI (%) | M1: Day Change ($) | N1: Day Change (%) | O1: Dividend Yield (%) | P1: Annual Dividend ($) | Q1: 52-Week Range | R1: Analyst Consensus
A2: HCLTECH.NS | B2: HCL TECH | C2: HCL Technologies Ltd | D2: Information Technology | E2: 150 | F2: 2023-02-14 | G2: 1120 | H2: 1745.5 | I2: =E2*G2 -> 0 | J2: =E2*H2 -> 0 | K2: =J2-I2 -> 0 | L2: =K2/I2 -> 0 | M2: 3240 | N2: 0.0125 | O2: 0.0315 | P2: =J2*O2 -> 0 | Q2: 1180 - 1820 | R2: 1950 (STRONG BUY)
A3: TCS.NS | B3: TCS | C3: Tata Consultancy Services | D3: Information Technology | E3: 40 | F3: 2023-01-10 | G3: 3350 | H3: 4120 | I3: =E3*G3 -> 0 | J3: =E3*H3 -> 0 | K3: =J3-I3 -> 0 | L3: =K3/I3 -> 0 | M3: 1680 | N3: 0.0103 | O3: 0.0195 | P3: =J3*O3 -> 0 | Q3: 3310 - 4590 | R3: 4600 (ACCUMULATE)
A4: INFY.NS | B4: INFOSYS | C4: Infosys Limited | D4: Information Technology | E4: 120 | F4: 2023-03-18 | G4: 1420 | H4: 1865 | I4: =E4*G4 -> 0 | J4: =E4*H4 -> 0 | K4: =J4-I4 -> 0 | L4: =K4/I4 -> 0 | M4: 2280 | N4: 0.0103 | O4: 0.024 | P4: =J4*O4 -> 0 | Q4: 1360 - 1980 | R4: 2100 (BUY)
A5: WIPRO.NS | B5: WIPRO | C5: Wipro Limited | D5: Information Technology | E5: 250 | F5: 2023-05-20 | G5: 410 | H5: 545 | I5: =E5*G5 -> 0 | J5: =E5*H5 -> 0 | K5: =J5-I5 -> 0 | L5: =K5/I5 -> 0 | M5: -875 | N5: -0.0064 | O5: 0.011 | P5: =J5*O5 -> 0 | Q5: 390 - 580 | R5: 620 (HOLD)
A6: TECHM.NS | B6: TECH MAHINDRA | C6: Tech Mahindra Ltd | D6: Information Technology | E6: 80 | F6: 2023-04-12 | G6: 1180 | H6: 1640 | I6: =E6*G6 -> 0 | J6: =E6*H6 -> 0 | K6: =J6-I6 -> 0 | L6: =K6/I6 -> 0 | M6: 1280 | N6: 0.0098 | O6: 0.0275 | P6: =J6*O6 -> 0 | Q6: 1110 - 1720 | R6: 1800 (BUY)
A7: HDFCBANK.NS | B7: HDFC BANK | C7: HDFC Bank Limited | D7: Banking & Financials | E7: 100 | F7: 2022-11-05 | G7: 1490 | H7: 1680 | I7: =E7*G7 -> 0 | J7: =E7*H7 -> 0 | K7: =J7-I7 -> 0 | L7: =K7/I7 -> 0 | M7: 1400 | N7: 0.0084 | O7: 0.0125 | P7: =J7*O7 -> 0 | Q7: 1380 - 1790 | R7: 1950 (STRONG BUY)
A8: AXISBANK.NS | B8: AXIS BANK | C8: Axis Bank Limited | D8: Banking & Financials | E8: 90 | F8: 2023-02-28 | G8: 960 | H8: 1265 | I8: =E8*G8 -> 0 | J8: =E8*H8 -> 0 | K8: =J8-I8 -> 0 | L8: =K8/I8 -> 0 | M8: 810 | N8: 0.0071 | O8: 0.009 | P8: =J8*O8 -> 0 | Q8: 940 - 1340 | R8: 1420 (BUY)
A9: COALINDIA.NS | B9: COAL INDIA | C9: Coal India Limited | D9: Energy & Mining | E9: 300 | F9: 2023-06-15 | G9: 280 | H9: 495 | I9: =E9*G9 -> 0 | J9: =E9*H9 -> 0 | K9: =J9-I9 -> 0 | L9: =K9/I9 -> 0 | M9: 1650 | N9: 0.0112 | O9: 0.052 | P9: =J9*O9 -> 0 | Q9: 270 - 540 | R9: 560 (BUY)
A10: RVNL.NS | B10: RVNL (RAIL VIKAS) | C10: Rail Vikas Nigam Limited | D10: Railways & Infrastructure | E10: 350 | F10: 2023-08-01 | G10: 175 | H10: 565 | I10: =E10*G10 -> 0 | J10: =E10*H10 -> 0 | K10: =J10-I10 -> 0 | L10: =K10/I10 -> 0 | M10: 4725 | N10: 0.0245 | O10: 0.0075 | P10: =J10*O10 -> 0 | Q10: 150 - 645 | R10: 700 (OUTPERFORM)
A11: IRFC.NS | B11: IRFC (INDIAN RAILWAY) | C11: Indian Railway Finance Corp | D11: Railways & Infrastructure | E11: 800 | F11: 2023-07-10 | G11: 75 | H11: 185 | I11: =E11*G11 -> 0 | J11: =E11*H11 -> 0 | K11: =J11-I11 -> 0 | L11: =K11/I11 -> 0 | M11: 2400 | N11: 0.0164 | O11: 0.018 | P11: =J11*O11 -> 0 | Q11: 68 - 229 | R11: 240 (BUY)
A12: ABCAPITAL.NS | B12: ADITYA BIRLA (ABCAPITAL) | C12: Aditya Birla Capital Ltd | D12: Conglomerate & Financials | E12: 400 | F12: 2023-09-05 | G12: 195 | H12: 405 | I12: =E12*G12 -> 0 | J12: =E12*H12 -> 0 | K12: =J12-I12 -> 0 | L12: =K12/I12 -> 0 | M12: 1200 | N12: 0.0075 | O12: 0.006 | P12: =J12*O12 -> 0 | Q12: 170 - 435 | R12: 480 (ACCUMULATE)

Sheet Historical_12M
A1: Stock Key | B1: Sector | C1: Month 1 | D1: Month 2 | E1: Month 3 | F1: Month 4 | G1: Month 5 | H1: Month 6 | I1: Month 7 | J1: Month 8 | K1: Month 9 | L1: Month 10 | M1: Month 11 | N1: Month 12 (Current)
A2: HCL TECH | B2: Information Technology | C2: 1180 | D2: 1220.5 | E2: 1265 | F2: 1310 | G2: 1420 | H2: 1485 | I2: 1540 | J2: 1610 | K2: 1660 | L2: 1715 | M2: 1730 | N2: 1745.5
A3: TCS | B3: Information Technology | C3: 3400 | D3: 3480 | E3: 3550 | F3: 3620 | G3: 3750 | H3: 3890 | I3: 3980 | J3: 4050 | K3: 4180 | L3: 4220 | M3: 4160 | N3: 4120
A4: INFOSYS | B4: Information Technology | C4: 1410 | D4: 1460 | E4: 1510 | F4: 1580 | G4: 1640 | H4: 1690 | I4: 1750 | J4: 1795 | K4: 1840 | L4: 1880 | M4: 1850 | N4: 1865
A5: WIPRO | B5: Information Technology | C5: 405 | D5: 420 | E5: 435 | F5: 450 | G5: 470 | H5: 495 | I5: 510 | J5: 525 | K5: 538 | L5: 555 | M5: 548 | N5: 545
A6: TECH MAHINDRA | B6: Information Technology | C6: 1150 | D6: 1200 | E6: 1260 | F6: 1310 | G6: 1390 | H6: 1450 | I6: 1510 | J6: 1580 | K6: 1620 | L6: 1660 | M6: 1650 | N6: 1640
A7: HDFC BANK | B7: Banking & Financials | C7: 1520 | D7: 1480 | E7: 1450 | F7: 1490 | G7: 1530 | H7: 1560 | I7: 1610 | J7: 1640 | K7: 1670 | L7: 1690 | M7: 1665 | N7: 1680
A8: AXIS BANK | B8: Banking & Financials | C8: 980 | D8: 1020 | E8: 1060 | F8: 1110 | G8: 1150 | H8: 1190 | I8: 1225 | J8: 1250 | K8: 1270 | L8: 1295 | M8: 1280 | N8: 1265
A9: COAL INDIA | B9: Energy & Mining | C9: 290 | D9: 320 | E9: 350 | F9: 390 | G9: 420 | H9: 445 | I9: 470 | J9: 485 | K9: 510 | L9: 525 | M9: 505 | N9: 495
A10: RVNL (RAIL VIKAS) | B10: Railways & Infrastructure | C10: 180 | D10: 210 | E10: 250 | F10: 290 | G10: 340 | H10: 390 | I10: 440 | J10: 490 | K10: 540 | L10: 590 | M10: 575 | N10: 565
A11: IRFC (INDIAN RAILWAY) | B11: Railways & Infrastructure | C11: 78 | D11: 92 | E11: 110 | F11: 130 | G11: 145 | H11: 160 | I11: 172 | J11: 185 | K11: 198 | L11: 205 | M11: 190 | N11: 185
A12: ADITYA BIRLA (ABCAPITAL) | B12: Conglomerate & Financials | C12: 200 | D12: 220 | E12: 245 | F12: 275 | G12: 310 | H12: 340 | I12: 365 | J12: 385 | K12: 410 | L12: 425 | M12: 415 | N12: 405

Sheet Dynamic_Feed
A1: Timeline / Month | B1: Jan | C1: Feb | D1: Mar | E1: Apr | F1: May | G1: Jun | H1: Jul | I1: Aug | J1: Sep | K1: Oct | L1: Nov | M1: Dec
A2: Selected Stock Price | B2: {=IF(Dashboard!$C$3="ALL PORTFOLIO (MASTER VIEW)", AVERAGE(Historical_12M!C$2:C$12), _xlfn.XLOOKUP(Dashboard!$C$3, Historical_12M!$A$2:$A$12, Historical_12M!C$2:C$12))} -> 0 | C2: {=IF(Dashboard!$C$3="ALL PORTFOLIO (MASTER VIEW)", AVERAGE(Historical_12M!D$2:D$12), _xlfn.XLOOKUP(Dashboard!$C$3, Historical_12M!$A$2:$A$12, Historical_12M!D$2:D$12))} -> 0 | D2: {=IF(Dashboard!$C$3="ALL PORTFOLIO (MASTER VIEW)", AVERAGE(Historical_12M!E$2:E$12), _xlfn.XLOOKUP(Dashboard!$C$3, Historical_12M!$A$2:$A$12, Historical_12M!E$2:E$12))} -> 0 | E2: {=IF(Dashboard!$C$3="ALL PORTFOLIO (MASTER VIEW)", AVERAGE(Historical_12M!F$2:F$12), _xlfn.XLOOKUP(Dashboard!$C$3, Historical_12M!$A$2:$A$12, Historical_12M!F$2:F$12))} -> 0 | F2: {=IF(Dashboard!$C$3="ALL PORTFOLIO (MASTER VIEW)", AVERAGE(Historical_12M!G$2:G$12), _xlfn.XLOOKUP(Dashboard!$C$3, Historical_12M!$A$2:$A$12, Historical_12M!G$2:G$12))} -> 0 | G2: {=IF(Dashboard!$C$3="ALL PORTFOLIO (MASTER VIEW)", AVERAGE(Historical_12M!H$2:H$12), _xlfn.XLOOKUP(Dashboard!$C$3, Historical_12M!$A$2:$A$12, Historical_12M!H$2:H$12))} -> 0 | H2: {=IF(Dashboard!$C$3="ALL PORTFOLIO (MASTER VIEW)", AVERAGE(Historical_12M!I$2:I$12), _xlfn.XLOOKUP(Dashboard!$C$3, Historical_12M!$A$2:$A$12, Historical_12M!I$2:I$12))} -> 0 | I2: {=IF(Dashboard!$C$3="ALL PORTFOLIO (MASTER VIEW)", AVERAGE(Historical_12M!J$2:J$12), _xlfn.XLOOKUP(Dashboard!$C$3, Historical_12M!$A$2:$A$12, Historical_12M!J$2:J$12))} -> 0 | ... M2: {=IF(Dashboard!$C$3="ALL PORTFOLIO (MASTER VIEW)", AVERAGE(Historical_12M!N$2:N$12), _xlfn.XLOOKUP(Dashboard!$C$3, Historical_12M!$A$2:$A$12, Historical_12M!N$2:N$12))} -> 0

Sheet Sector_Summary
A1: Industry Sector | B1: Total Market Value | C1: Allocation (%) | D1: Unrealized Gain | E1: Holdings Count
A2: Information Technology | B2: =SUMIF(Holdings_Data!$D$2:$D$12, A2, Holdings_Data!$J$2:$J$12) -> 0 | C2: =B2/Dashboard!$F$17 -> 0 | D2: =SUMIF(Holdings_Data!$D$2:$D$12, A2, Holdings_Data!$K$2:$K$12) -> 0 | E2: =COUNTIF(Holdings_Data!$D$2:$D$12, A2) -> 0
A3: Banking & Financials | B3: =SUMIF(Holdings_Data!$D$2:$D$12, A3, Holdings_Data!$J$2:$J$12) -> 0 | C3: =B3/Dashboard!$F$17 -> 0 | D3: =SUMIF(Holdings_Data!$D$2:$D$12, A3, Holdings_Data!$K$2:$K$12) -> 0 | E3: =COUNTIF(Holdings_Data!$D$2:$D$12, A3) -> 0
A4: Energy & Mining | B4: =SUMIF(Holdings_Data!$D$2:$D$12, A4, Holdings_Data!$J$2:$J$12) -> 0 | C4: =B4/Dashboard!$F$17 -> 0 | D4: =SUMIF(Holdings_Data!$D$2:$D$12, A4, Holdings_Data!$K$2:$K$12) -> 0 | E4: =COUNTIF(Holdings_Data!$D$2:$D$12, A4) -> 0
A5: Railways & Infrastructure | B5: =SUMIF(Holdings_Data!$D$2:$D$12, A5, Holdings_Data!$J$2:$J$12) -> 0 | C5: =B5/Dashboard!$F$17 -> 0 | D5: =SUMIF(Holdings_Data!$D$2:$D$12, A5, Holdings_Data!$K$2:$K$12) -> 0 | E5: =COUNTIF(Holdings_Data!$D$2:$D$12, A5) -> 0
A6: Conglomerate & Financials | B6: =SUMIF(Holdings_Data!$D$2:$D$12, A6, Holdings_Data!$J$2:$J$12) -> 0 | C6: =B6/Dashboard!$F$17 -> 0 | D6: =SUMIF(Holdings_Data!$D$2:$D$12, A6, Holdings_Data!$K$2:$K$12) -> 0 | E6: =COUNTIF(Holdings_Data!$D$2:$D$12, A6) -> 0

Sheet Return_Analytics
B2: PORTFOLIO RETURN & RISK ANALYZER (INDIAN EQUITIES)
B3: Total Portfolio Capital Invested | C3: =SUM(Holdings_Data!I2:I12) -> 0 | D3: Total capital deployed across 11 Indian stocks
B4: Current Portfolio Market Valuation | C4: =SUM(Holdings_Data!J2:J12) -> 0 | D4: Live aggregate market valuation of portfolio
B5: Total Unrealized Capital Profit / Gain | C5: =C4-C3 -> 0 | D5: Net paper profits generated to date
B6: All-Time Return on Investment (ROI %) | C6: =C5/C3 -> 0 | D6: Overall capital appreciation return percentage
B7: Portfolio Compound Annual Growth (CAGR Est.) | C7: 0.284 | D7: Annualized growth benchmarked to holding timeline
B8: Total Annual Dividend Cashflow | C8: =SUM(Holdings_Data!P2:P12) -> 0 | D8: Expected annual passive cash dividend payout
B9: Portfolio Weighted Dividend Yield | C9: =C8/C4 -> 0 | D9: Dividend yield percentage relative to current valuation
B10: Portfolio Beta vs Nifty 50 Index | C10: 1.04 | D10: Market sensitivity rating relative to NIFTY 50
B11: Sharpe Ratio (Risk-Adjusted Performance) | C11: 2.12 | D11: Excess risk-adjusted return (>2.0 indicates outstanding)
B12: Top Multi-Bagger Asset (Highest ROI) | C12: RVNL (+222.8%) | D12: Leading wealth generator in portfolio
B13: Top Allocation Holding by Weight | C13: HCL TECH (19.4%) | D13: Largest capital allocation exposure
B14: Portfolio Diversification Health (HHI) | C14: 0.14 (Highly Diversified) | D14: Optimal distribution across 5 core sectors

Sheet User_Guide
B2: Stock Market Portfolio Tracker - User Guide & Features
B3: 1. Interactive Stock Dropdown | C3: Click on cell C3 in the Dashboard sheet. Select ANY stock (e.g. HCL TECH, TCS, WIPRO, RVNL, IRFC, HDFC BANK, etc.). Every single KPI card, the Inspection Panel, and the 12-Month Performance Chart will update dynamically!
B4: 2. Master View Option | C4: To view your entire portfolio combined, pick "ALL PORTFOLIO (MASTER VIEW)" from the dropdown in C3.
B5: 3. Rich Graphs & Visuals Included | C5: Includes: 1) Sector Donut Chart, 2) Individual Asset Pie Chart, 3) Sector Horizontal Bar Chart, 4) Dynamic 12M Area Trend Chart, 5) Multi-Stock Historical Line Chart, and 6) In-cell Data Bars & Sparklines.
B6: 4. Live Formulas (XLOOKUP & SUMIF) | C6: The dashboard uses modern Excel formulas (=XLOOKUP, =SUMIF, =COUNTIF, =AVERAGE) ensuring full automation with zero hardcoded metrics.
B7: 5. Generous Column Widths | C7: All numbers, currency figures, and profit metrics are formatted with ample cell widths to ensure zero "###" truncation across all Excel viewports.
B8: 6. Return & Risk Analytics Sheet | C8: Check the "Return_Analytics" sheet for in-depth metrics including Portfolio CAGR, Sharpe Ratio, Dividend Cashflow, and Beta vs Nifty 50.
